palshellpy/__init__.py
palshellpy/cmd_runner.py
palshellpy-0.1.2.dist-info/entry_points.txt
palshellpy-0.1.2.dist-info/licenses/LICENSE.txt
palshellpy-0.1.2.dist-info/WHEEL
palshellpy-0.1.2.dist-info/METADATA
palshellpy-0.1.2.dist-info/RECORD
