Metadata-Version: 2.4
Name: palshellpy
Version: 0.1.2
Summary: A shell lib
Author-email: Tiny Twist <tiny.mahua@gmail.com>
Maintainer-email: Tiny Twist <tiny.mahua@gmail.com>
Requires-Python: >= 3.6
License-File: LICENSE.txt
